ihex.py
setup.py
IHex.egg-info/PKG-INFO
IHex.egg-info/SOURCES.txt
IHex.egg-info/dependency_links.txt
IHex.egg-info/top_level.txt