Metadata-Version: 1.0
Name: IHex
Version: 0.1.3
Summary: A Python library for reading and writing Intel Hex files
Home-page: https://github.com/kierdavis/IHex
Author: Kier Davis
Author-email: kierdavis@gmail.com
License: UNKNOWN
Keywords: intel hex binary files
Platform: UNKNOWN
Classifier: Programming Language :: Python
Classifier: Operating System :: OS Independent
Classifier: Topic :: Software Development :: Libraries :: Python Modules
